setup.py
SocialKit/__init__.py
SocialKit/agents.py
SocialKit/config.py
SocialKit/geo.py
SocialKit/libs.py
SocialKit/log.py
SocialKit/parser.py
SocialKit/phantomjs.py
SocialKit/rss.py
SocialKit/searcher.py
SocialKit.egg-info/PKG-INFO
SocialKit.egg-info/SOURCES.txt
SocialKit.egg-info/dependency_links.txt
SocialKit.egg-info/not-zip-safe
SocialKit.egg-info/requires.txt
SocialKit.egg-info/top_level.txt