Metadata-Version: 1.0
Name: SocialKit
Version: 0.5.5
Summary: a socialkit libs
Home-page: http://github.com/
Author: Froy
Author-email: no_email@mail.web.com
License: MIT
Platform: UNKNOWN
